OneDriveHelper/__init__.py
OneDriveHelper/config/__init__.py
OneDriveHelper/config/config.py
OneDriveHelper/exceptions/OneDriverExceptions.py
OneDriveHelper/exceptions/__init__.py
OneDriveHelper/modules/__init__.py
OneDriveHelper/modules/onedrive_helper.py
OneDriveHelper/test/__init__.py
OneDriveHelper/test/test_onedriver.py
OneDriveHelper/test/test_test.py
OneDriveHelper-1.0.0.dist-info/LICENSE
OneDriveHelper-1.0.0.dist-info/METADATA
OneDriveHelper-1.0.0.dist-info/WHEEL
OneDriveHelper-1.0.0.dist-info/top_level.txt
OneDriveHelper-1.0.0.dist-info/RECORD
